asreview_dory-1.2.2.dist-info/licenses/LICENSE
asreviewcontrib/dory/__init__.py
asreviewcontrib/dory/_metadata.py
asreviewcontrib/dory/_version.py
asreviewcontrib/dory/entrypoint.py
asreviewcontrib/dory/classifiers/__init__.py
asreviewcontrib/dory/classifiers/adaboost.py
asreviewcontrib/dory/classifiers/neural_networks.py
asreviewcontrib/dory/classifiers/xgboost.py
asreviewcontrib/dory/feature_extractors/__init__.py
asreviewcontrib/dory/feature_extractors/doc2vec.py
asreviewcontrib/dory/feature_extractors/huggingface_embeddings.py
asreviewcontrib/dory/feature_extractors/sentence_transformer_embeddings.py
asreviewcontrib/dory/feature_extractors/utils.py
asreview_dory-1.2.2.dist-info/METADATA
asreview_dory-1.2.2.dist-info/WHEEL
asreview_dory-1.2.2.dist-info/entry_points.txt
asreview_dory-1.2.2.dist-info/top_level.txt
asreview_dory-1.2.2.dist-info/RECORD
