Metadata-Version: 2.4
Name: asreview-dory
Version: 1.2.2
Summary: ASReview New Exciting Models
Author-email: ASReview LAB developers <asreview@uu.nl>
License: MIT
Project-URL: Homepage, https://asreview.ai
Project-URL: Repository, https://github.com/asreview/asreview-dory/
Project-URL: Issues, https://github.com/asreview/asreview-dory/issues
Classifier: Development Status :: 5 - Production/Stable
Classifier: License :: OSI Approved :: MIT License
Classifier: Programming Language :: Python :: 3
Classifier: Programming Language :: Python :: 3.10
Classifier: Programming Language :: Python :: 3.11
Classifier: Programming Language :: Python :: 3.12
Classifier: Programming Language :: Python :: 3.13
Classifier: Topic :: Scientific/Engineering :: Artificial Intelligence
Classifier: Topic :: Scientific/Engineering :: Information Analysis
Classifier: Topic :: Text Processing :: General
Requires-Python: >=3.10
License-File: LICENSE
Requires-Dist: asreview>=2.0
Requires-Dist: keras>=3.8.0
Requires-Dist: numpy
Requires-Dist: scikit-learn>=1.6.1
Requires-Dist: sentence-transformers>=3.4.1
Requires-Dist: accelerate>=1.0.0
Requires-Dist: torch>=2.1.0
Requires-Dist: xgboost>=2.1.4
Requires-Dist: gensim>=4.4.0
Dynamic: license-file
